{
  "computed_at": "2026-06-06T21:58:38.286868Z",
  "holdings": [
    {
      "name": "AST SpaceMobile",
      "ticker": "ASTS",
      "zakaatable_pct": 8.2782,
      "zakaatable_pct_broad": 8.2782,
      "zakaatable_pct_assets_only": 8.6463,
      "current_price": 93.6,
      "price_gbp": 69.9713,
      "trading_currency": "USD",
      "fallback": false,
      "error": null,
      "bs_date": "2026-03-31",
      "market_cap": 36328460288,
      "financial_currency": "USD",
      "assets": {
        "cash_and_sti": 3029591000.0,
        "receivables": 27453000.0,
        "inventory": 16756000.0,
        "other_current": 67253000.0,
        "total": 3141053000.0
      },
      "assets_broad": {
        "nc_investments": 0.0,
        "nc_deferred_tax_asset": 0.0,
        "nc_receivables": 0.0,
        "nc_liquid_total": 0.0,
        "total": 3141053000.0
      },
      "liabilities": {
        "payables": 60850000.0,
        "current_debt": 8236000.0,
        "accrued_expenses": 64609000.0,
        "taxes_payable": 0.0,
        "total": 133695000.0
      },
      "net_zakaatable": 3007358000.0,
      "net_zakaatable_broad": 3007358000.0,
      "net_zakaatable_assets_only": 3141053000.0
    },
    {
      "name": "NVIDIA",
      "ticker": "NVDA",
      "zakaatable_pct": 2.2941,
      "zakaatable_pct_broad": 3.4027,
      "zakaatable_pct_assets_only": 4.1481,
      "current_price": 205.1,
      "price_gbp": 153.3239,
      "trading_currency": "USD",
      "fallback": false,
      "error": null,
      "bs_date": "2026-04-30",
      "market_cap": 4967727366144,
      "financial_currency": "USD",
      "assets": {
        "cash_and_sti": 80572000000.0,
        "receivables": 40710000000.0,
        "inventory": 25797000000.0,
        "other_current": 3916000000.0,
        "total": 150995000000.0
      },
      "assets_broad": {
        "nc_investments": 43364000000.0,
        "nc_deferred_tax_asset": 11707000000.0,
        "nc_receivables": 0.0,
        "nc_liquid_total": 55071000000.0,
        "total": 206066000000.0
      },
      "liabilities": {
        "payables": 13097000000.0,
        "current_debt": 1000000000.0,
        "accrued_expenses": 12293000000.0,
        "taxes_payable": 10638000000.0,
        "total": 37028000000.0
      },
      "net_zakaatable": 113967000000.0,
      "net_zakaatable_broad": 169038000000.0,
      "net_zakaatable_assets_only": 206066000000.0
    },
    {
      "name": "Alphabet (Class A)",
      "ticker": "GOOGL",
      "zakaatable_pct": 2.7659,
      "zakaatable_pct_broad": 5.1899,
      "zakaatable_pct_assets_only": 7.1802,
      "current_price": 368.53,
      "price_gbp": 275.4972,
      "trading_currency": "USD",
      "fallback": false,
      "error": null,
      "bs_date": "2026-03-31",
      "market_cap": 4494199357440,
      "financial_currency": "USD",
      "assets": {
        "cash_and_sti": 126840000000.0,
        "receivables": 62999000000.0,
        "inventory": 0.0,
        "other_current": 23914000000.0,
        "total": 213753000000.0
      },
      "assets_broad": {
        "nc_investments": 106946000000.0,
        "nc_deferred_tax_asset": 1995000000.0,
        "nc_receivables": 0.0,
        "nc_liquid_total": 108941000000.0,
        "total": 322694000000.0
      },
      "liabilities": {
        "payables": 16852000000.0,
        "current_debt": 0.0,
        "accrued_expenses": 68691000000.0,
        "taxes_payable": 3905000000.0,
        "total": 89448000000.0
      },
      "net_zakaatable": 124305000000.0,
      "net_zakaatable_broad": 233246000000.0,
      "net_zakaatable_assets_only": 322694000000.0
    },
    {
      "name": "Meta Platforms",
      "ticker": "META",
      "zakaatable_pct": 4.3464,
      "zakaatable_pct_broad": 6.2338,
      "zakaatable_pct_assets_only": 9.1793,
      "current_price": 593.0,
      "price_gbp": 443.3013,
      "trading_currency": "USD",
      "fallback": false,
      "error": null,
      "bs_date": "2026-03-31",
      "market_cap": 1505284980736,
      "financial_currency": "USD",
      "assets": {
        "cash_and_sti": 81180000000.0,
        "receivables": 17470000000.0,
        "inventory": 0.0,
        "other_current": 11115000000.0,
        "total": 109765000000.0
      },
      "assets_broad": {
        "nc_investments": 28410000000.0,
        "nc_deferred_tax_asset": 0.0,
        "nc_receivables": 0.0,
        "nc_liquid_total": 28410000000.0,
        "total": 138175000000.0
      },
      "liabilities": {
        "payables": 13326000000.0,
        "current_debt": 0.0,
        "accrued_expenses": 31013000000.0,
        "taxes_payable": 0.0,
        "total": 44339000000.0
      },
      "net_zakaatable": 65426000000.0,
      "net_zakaatable_broad": 93836000000.0,
      "net_zakaatable_assets_only": 138175000000.0
    },
    {
      "name": "Apple",
      "ticker": "AAPL",
      "zakaatable_pct": 1.6938,
      "zakaatable_pct_broad": 3.4237,
      "zakaatable_pct_assets_only": 4.9225,
      "current_price": 307.34,
      "price_gbp": 229.7542,
      "trading_currency": "USD",
      "fallback": false,
      "error": null,
      "bs_date": "2026-03-31",
      "market_cap": 4514011676672,
      "financial_currency": "USD",
      "assets": {
        "cash_and_sti": 68507000000.0,
        "receivables": 53511000000.0,
        "inventory": 6747000000.0,
        "other_current": 15349000000.0,
        "total": 144114000000.0
      },
      "assets_broad": {
        "nc_investments": 78088000000.0,
        "nc_deferred_tax_asset": 0.0,
        "nc_receivables": 0.0,
        "nc_liquid_total": 78088000000.0,
        "total": 222202000000.0
      },
      "liabilities": {
        "payables": 57349000000.0,
        "current_debt": 10307000000.0,
        "accrued_expenses": 0.0,
        "taxes_payable": 0.0,
        "total": 67656000000.0
      },
      "net_zakaatable": 76458000000.0,
      "net_zakaatable_broad": 154546000000.0,
      "net_zakaatable_assets_only": 222202000000.0
    },
    {
      "name": "Microsoft",
      "ticker": "MSFT",
      "zakaatable_pct": 4.0505,
      "zakaatable_pct_broad": 5.1387,
      "zakaatable_pct_assets_only": 6.7513,
      "current_price": 416.67,
      "price_gbp": 311.4846,
      "trading_currency": "USD",
      "fallback": false,
      "error": null,
      "bs_date": "2026-03-31",
      "market_cap": 3095206035456,
      "financial_currency": "USD",
      "assets": {
        "cash_and_sti": 78228000000.0,
        "receivables": 60041000000.0,
        "inventory": 1219000000.0,
        "other_current": 35797000000.0,
        "total": 175285000000.0
      },
      "assets_broad": {
        "nc_investments": 33683000000.0,
        "nc_deferred_tax_asset": 0.0,
        "nc_receivables": 0.0,
        "nc_liquid_total": 33683000000.0,
        "total": 208968000000.0
      },
      "liabilities": {
        "payables": 37513000000.0,
        "current_debt": 8839000000.0,
        "accrued_expenses": 0.0,
        "taxes_payable": 3563000000.0,
        "total": 49915000000.0
      },
      "net_zakaatable": 125370000000.0,
      "net_zakaatable_broad": 159053000000.0,
      "net_zakaatable_assets_only": 208968000000.0
    },
    {
      "name": "Amazon",
      "ticker": "AMZN",
      "zakaatable_pct": 2.2401,
      "zakaatable_pct_broad": 2.2401,
      "zakaatable_pct_assets_only": 9.641,
      "current_price": 246.03,
      "price_gbp": 183.9214,
      "trading_currency": "USD",
      "fallback": false,
      "error": null,
      "bs_date": "2026-03-31",
      "market_cap": 2646571745280,
      "financial_currency": "USD",
      "assets": {
        "cash_and_sti": 143089000000.0,
        "receivables": 75532000000.0,
        "inventory": 36534000000.0,
        "other_current": 0.0,
        "total": 255155000000.0
      },
      "assets_broad": {
        "nc_investments": 0.0,
        "nc_deferred_tax_asset": 0.0,
        "nc_receivables": 0.0,
        "nc_liquid_total": 0.0,
        "total": 255155000000.0
      },
      "liabilities": {
        "payables": 124749000000.0,
        "current_debt": 0.0,
        "accrued_expenses": 71120000000.0,
        "taxes_payable": 0.0,
        "total": 195869000000.0
      },
      "net_zakaatable": 59286000000.0,
      "net_zakaatable_broad": 59286000000.0,
      "net_zakaatable_assets_only": 255155000000.0
    },
    {
      "name": "Rocket Lab",
      "ticker": "RKLB",
      "zakaatable_pct": 2.4057,
      "zakaatable_pct_broad": 2.5429,
      "zakaatable_pct_assets_only": 2.6834,
      "current_price": 110.08,
      "price_gbp": 82.2911,
      "trading_currency": "USD",
      "fallback": false,
      "error": null,
      "bs_date": "2026-03-31",
      "market_cap": 68780048384,
      "financial_currency": "USD",
      "assets": {
        "cash_and_sti": 1383351000.0,
        "receivables": 175210000.0,
        "inventory": 183146000.0,
        "other_current": 9614000.0,
        "total": 1751321000.0
      },
      "assets_broad": {
        "nc_investments": 93494000.0,
        "nc_deferred_tax_asset": 849000.0,
        "nc_receivables": 0.0,
        "nc_liquid_total": 94343000.0,
        "total": 1845664000.0
      },
      "liabilities": {
        "payables": 63112000.0,
        "current_debt": 0.0,
        "accrued_expenses": 33546000.0,
        "taxes_payable": 0.0,
        "total": 96658000.0
      },
      "net_zakaatable": 1654663000.0,
      "net_zakaatable_broad": 1749006000.0,
      "net_zakaatable_assets_only": 1845664000.0
    },
    {
      "name": "Atos",
      "ticker": "ATO.PA",
      "zakaatable_pct": 100,
      "zakaatable_pct_broad": 100,
      "zakaatable_pct_assets_only": 100,
      "current_price": 37.52,
      "price_gbp": 32.413,
      "trading_currency": "EUR",
      "fallback": false,
      "error": null,
      "bs_date": "2025-12-31",
      "market_cap": 728356800,
      "financial_currency": "EUR",
      "assets": {
        "cash_and_sti": 1116000000.0,
        "receivables": 1361000000.0,
        "inventory": 37000000.0,
        "other_current": 602000000.0,
        "total": 3116000000.0
      },
      "assets_broad": {
        "nc_investments": 66000000.0,
        "nc_deferred_tax_asset": 124000000.0,
        "nc_receivables": 0.0,
        "nc_liquid_total": 190000000.0,
        "total": 3306000000.0
      },
      "liabilities": {
        "payables": 272000000.0,
        "current_debt": 23000000.0,
        "accrued_expenses": 0.0,
        "taxes_payable": 350000000.0,
        "total": 645000000.0
      },
      "net_zakaatable": 2471000000.0,
      "net_zakaatable_broad": 2661000000.0,
      "net_zakaatable_assets_only": 3306000000.0
    }
  ]
}